README.md
setup.py
omni_ai_3d_studio/__init__.py
omni_ai_3d_studio/config.py
omni_ai_3d_studio/tasks.py
omni_ai_3d_studio/utils.py
omni_ai_3d_studio.egg-info/PKG-INFO
omni_ai_3d_studio.egg-info/SOURCES.txt
omni_ai_3d_studio.egg-info/dependency_links.txt
omni_ai_3d_studio.egg-info/requires.txt
omni_ai_3d_studio.egg-info/top_level.txt