Metadata-Version: 2.1
Name: omni-ai-3d-studio
Version: 0.1.0
Summary: A package for AI-powered 3D model generation and image upscaling
Author: Adhithyan J
Author-email: adhijag54@gmail.com
License: MIT
Requires-Dist: Flask
Requires-Dist: celery
Requires-Dist: redis
Requires-Dist: pika
Requires-Dist: cloudinary
Requires-Dist: requests
Requires-Dist: pymeshlab
Requires-Dist: replicate
